scl_parser/__init__.py
scl_parser/api.py
scl_parser/errors.py
scl_parser/lexer.py
scl_parser/parser.py
scl_parser/parser_core.py
scl_parser/serializer.py
scl_parser/tokens.py
structcfg_parser-1.1.0.dist-info/licenses/LICENSE
structcfg_parser-1.1.0.dist-info/METADATA
structcfg_parser-1.1.0.dist-info/WHEEL
structcfg_parser-1.1.0.dist-info/top_level.txt
structcfg_parser-1.1.0.dist-info/RECORD
