Metadata-Version: 2.4
Name: structcfg-parser
Version: 1.1.0
Summary: Parser for Structured Configuration Language (SCL)
Home-page: https://gitlab.com/shareui/scl
Author: shareui
License: MIT
Project-URL: Homepage, https://gitlab.com/shareui/scl
Project-URL: Bug Reports, https://discord.com/users/1367967801125376143
Project-URL: Source, https://gitlab.com/shareui/scl
Keywords: parser,configuration,scl,config,structured-config
Classifier: Development Status :: 4 - Beta
Classifier: Intended Audience :: Developers
Classifier: Topic :: Software Development :: Libraries :: Python Modules
Classifier: License :: OSI Approved :: MIT License
Classifier: Programming Language :: Python :: 3
Classifier: Programming Language :: Python :: 3.7
Classifier: Programming Language :: Python :: 3.8
Classifier: Programming Language :: Python :: 3.9
Classifier: Programming Language :: Python :: 3.10
Classifier: Programming Language :: Python :: 3.11
Classifier: Programming Language :: Python :: 3.12
Requires-Python: >=3.7
License-File: LICENSE
Dynamic: home-page
Dynamic: license-file
Dynamic: requires-python
